and/and.v
module And(input_1, input_2, out);
	input input_1;
	input input_2;
	output out;

	wire input_1;
	wire input_2;
	wire out;

	wire intermediary;
	wire out_nand;
	
	nmos n1(intermediary, 0, input_2);
	nmos n2(out_nand, intermediary, input_1);

	pmos p1(out_nand, 1, input_1);
	pmos p2(out_nand, 1, input_2);

	nmos n3(out, 0, out_nand);
	pmos p3(out, 1, out_nand);
endmodule

and/and_tb.v
module test;
	initial begin
		# 100 $finish;
	end
	
	reg input_1 = 0;
	reg input_2 = 0;

	reg out = 0;
	
	wire w_out;
	
	And a1(input_1, input_2, w_out);
	
	always
	begin
		#5 input_1 = 1; // Input 1 : 1, Input 2 : 0 
		#5 input_2 = 1; 
		#0 input_1 = 0; // Input 1 : 0, Input 2 : 1
		#5 input_1 = 1; // Input 1 : 1, Input 2 : 1
		#5 input_1 = 0;
		#0 input_2 = 0; // Input 1 : 0, Input 2 : 0
	end
		
	always @(posedge input_1, posedge input_2)
	begin
		assign out = w_out;
	end
	
	initial begin
		$dumpfile("and.vcd");
		$dumpvars(0, test);
		$monitor("At time %t, input_1 = (%0d), input_2 = (%0d), output = (%0d)", $time, input_1, input_2, out);
	end
endmodule

and/and.vcd
$date
	Tue Jun 25 01:00:32 2019
$end
$version
	Icarus Verilog
$end
$timescale
	1s
$end
$scope module test $end
$var wire 1 ! w_out $end
$var reg 1 " input_1 $end
$var reg 1 # input_2 $end
$var reg 1 $ out $end
$scope module a1 $end
$var wire 1 " input_1 $end
$var wire 1 # input_2 $end
$var wire 1 % intermediary $end
$var wire 1 ! out $end
$var wire 1 & out_nand $end
$upscope $end
$upscope $end
$enddefinitions $end
#0
$dumpvars
1&
z%
0$
0#
0"
0!
$end
#5
1"
#10
0"
0%
0$
0!
1&
1#
#15
1$
1!
0&
1"
#20
z%
0#
0$
0!
1&
0"
#25
1"
#30
0"
0%
0$
0!
1&
1#
#35
1$
1!
0&
1"
#40
z%
0#
0$
0!
1&
0"
#45
1"
#50
0"
0%
0$
0!
1&
1#
#55
1$
1!
0&
1"
#60
z%
0#
0$
0!
1&
0"
#65
1"
#70
0"
0%
0$
0!
1&
1#
#75
1$
1!
0&
1"
#80
z%
0#
0$
0!
1&
0"
#85
1"
#90
0"
0%
0$
0!
1&
1#
#95
1$
1!
0&
1"
#100
z%
0#
0$
0!
1&
0"
