xnor/xnor.v
module Xnor(input_1, input_2, out);
	input input_1;
	input input_2;
	output out;

	wire input_1;
	wire input_2;
	wire out;

	wire junc_1;
	wire intermediary;

	nmos n1(junc_1, 0, input_1);
	pmos p1(junc_1, 1, input_1);
	
	nmos n2(intermediary, junc_1, input_2);
	pmos p2(intermediary, input_1, input_2);
	
	nmos n3(out, 0, intermediary);
	pmos p3(out, 1, intermediary);
endmodule

xnor/xnor_tb.v
module test;
	initial begin
		# 100 $finish;
	end
	
	reg input_1 = 0;
	reg input_2 = 0;

	reg out = 0;
	
	wire w_out;
	
	Xnor x1(input_1, input_2, w_out);
	
	always
	begin
		#5 input_1 = 1; // Input 1 : 1, Input 2 : 0 
		#5 input_2 = 1; 
		#0 input_1 = 0; // Input 1 : 0, Input 2 : 1
		#5 input_1 = 1; // Input 1 : 1, Input 2 : 1
		#5 input_1 = 0;
		#0 input_2 = 0; // Input 1 : 0, Input 2 : 0
	end
		
	always @(posedge input_1, posedge input_2)
	begin
		assign out = w_out;
	end
	
	initial begin
		$dumpfile("xnor.vcd");
		$dumpvars(0, test);
		$monitor("At time %t, input_1 = (%0d), input_2 = (%0d), output = (%0d)", $time, input_1, input_2, out);
	end
endmodule

xnor/xnor.vcd
$date
	Tue Jun 25 00:37:49 2019
$end
$version
	Icarus Verilog
$end
$timescale
	1s
$end
$scope module test $end
$var wire 1 ! w_out $end
$var reg 1 " input_1 $end
$var reg 1 # input_2 $end
$var reg 1 $ out $end
$scope module x1 $end
$var wire 1 " input_1 $end
$var wire 1 # input_2 $end
$var wire 1 % intermediary $end
$var wire 1 & junc_1 $end
$var wire 1 ! out $end
$upscope $end
$upscope $end
$enddefinitions $end
#0
$dumpvars
1&
0%
0$
0#
0"
1!
$end
#5
0&
0!
1%
1"
#10
1&
0"
0$
0!
1%
1#
#15
1$
1!
0%
0&
1"
#20
0#
1$
1!
0%
1&
0"
#25
0&
0$
0!
1%
1"
#30
1&
0"
0$
0!
1%
1#
#35
1$
1!
0%
0&
1"
#40
0#
1$
1!
0%
1&
0"
#45
0&
0$
0!
1%
1"
#50
1&
0"
0$
0!
1%
1#
#55
1$
1!
0%
0&
1"
#60
0#
1$
1!
0%
1&
0"
#65
0&
0$
0!
1%
1"
#70
1&
0"
0$
0!
1%
1#
#75
1$
1!
0%
0&
1"
#80
0#
1$
1!
0%
1&
0"
#85
0&
0$
0!
1%
1"
#90
1&
0"
0$
0!
1%
1#
#95
1$
1!
0%
0&
1"
#100
0#
1$
1!
0%
1&
0"
