nand/nand.v
module Nand(input_1, input_2, out);
	input input_1;
	input input_2;
	output out;

	wire input_1;
	wire input_2;
	wire out;

	wire intermediary;

	nmos n1(intermediary, 0, input_2);
	nmos n2(out, intermediary, input_1);

	pmos p1(out, 1, input_1);
	pmos p2(out, 1, input_2);
endmodule

not/not.v
module Not(in, out);
	output out;
	input in;

	wire out;
	wire in;
	
	nmos n1(out, 0, in);
    pmos p1(out, 1, in);
endmodule

d_latch/d_latch.v
module D_latch(D, Q, clk);
	input clk;
	input D;
	output Q;
	output Q_dot;
	
	wire D;
	wire R;
	wire Q;
	wire Q_dot;

	wire s_gated;
	wire r_gated;	
		
	Not nt1(D, R);

	Nand a1(D, clk, s_gated);
	Nand a2(R, clk, r_gated);

	Nand n1(s_gated, Q_dot, Q);
	Nand n2(r_gated, Q, Q_dot);
endmodule

d_latch/d_latch_tb.v
module test;
	initial begin
		# 100 $finish;
	end
	
	reg clk = 0;	
	reg set = 0;
	reg out = 0;
	
	wire w_out;
	
	D_latch s1(set, w_out, clk);
	
	always
	begin
		#2 set = 1;
		#2 set = 0;
	end
	
	always
	begin
		#3 clk = !clk;
	end
	
	always @(posedge set)
	begin
		assign out = w_out;
	end

	initial begin
		$dumpfile("d_latch.vcd");
		$dumpvars(0, test);
		$monitor("At time %t, set = (%0d), output = (%0d), clk = (%0d)", $time, set, out, clk);
	end
endmodule

d_latch/d_latch.vcd
$date
	Tue Jun 25 22:59:09 2019
$end
$version
	Icarus Verilog
$end
$timescale
	1s
$end
$scope module test $end
$var wire 1 ! w_out $end
$var reg 1 " clk $end
$var reg 1 # out $end
$var reg 1 $ set $end
$scope module s1 $end
$var wire 1 $ D $end
$var wire 1 ! Q $end
$var wire 1 % Q_dot $end
$var wire 1 & R $end
$var wire 1 " clk $end
$var wire 1 ' r_gated $end
$var wire 1 ( s_gated $end
$scope module a1 $end
$var wire 1 $ input_1 $end
$var wire 1 " input_2 $end
$var wire 1 ) intermediary $end
$var wire 1 ( out $end
$upscope $end
$scope module a2 $end
$var wire 1 & input_1 $end
$var wire 1 " input_2 $end
$var wire 1 * intermediary $end
$var wire 1 ' out $end
$upscope $end
$scope module n1 $end
$var wire 1 ( input_1 $end
$var wire 1 % input_2 $end
$var wire 1 + intermediary $end
$var wire 1 ! out $end
$upscope $end
$scope module n2 $end
$var wire 1 ' input_1 $end
$var wire 1 ! input_2 $end
$var wire 1 , intermediary $end
$var wire 1 % out $end
$upscope $end
$scope module nt1 $end
$var wire 1 $ in $end
$var wire 1 & out $end
$upscope $end
$upscope $end
$upscope $end
$enddefinitions $end
#0
$dumpvars
x,
x+
z*
z)
1(
1'
1&
x%
0$
0#
0"
x!
$end
#2
x#
0&
1$
#3
0,
z+
0%
1#
1!
0)
0(
0*
1"
#4
z,
0#
0!
1(
0+
1%
0'
1&
0$
#6
0&
1$
z)
z*
1'
0"
#8
1&
0$
#9
0)
0*
0'
1"
#10
0,
z+
0%
1#
1!
0(
1'
0&
1$
#12
1&
0$
z)
1(
z*
0"
#14
0&
1$
#15
0)
0(
0*
1"
#16
z,
0#
0!
1(
0+
1%
0'
1&
0$
#18
0&
1$
z)
z*
1'
0"
#20
1&
0$
#21
0)
0*
0'
1"
#22
0,
z+
0%
1#
1!
0(
1'
0&
1$
#24
1&
0$
z)
1(
z*
0"
#26
0&
1$
#27
0)
0(
0*
1"
#28
z,
0#
0!
1(
0+
1%
0'
1&
0$
#30
0&
1$
z)
z*
1'
0"
#32
1&
0$
#33
0)
0*
0'
1"
#34
0,
z+
0%
1#
1!
0(
1'
0&
1$
#36
1&
0$
z)
1(
z*
0"
#38
0&
1$
#39
0)
0(
0*
1"
#40
z,
0#
0!
1(
0+
1%
0'
1&
0$
#42
0&
1$
z)
z*
1'
0"
#44
1&
0$
#45
0)
0*
0'
1"
#46
0,
z+
0%
1#
1!
0(
1'
0&
1$
#48
1&
0$
z)
1(
z*
0"
#50
0&
1$
#51
0)
0(
0*
1"
#52
z,
0#
0!
1(
0+
1%
0'
1&
0$
#54
0&
1$
z)
z*
1'
0"
#56
1&
0$
#57
0)
0*
0'
1"
#58
0,
z+
0%
1#
1!
0(
1'
0&
1$
#60
1&
0$
z)
1(
z*
0"
#62
0&
1$
#63
0)
0(
0*
1"
#64
z,
0#
0!
1(
0+
1%
0'
1&
0$
#66
0&
1$
z)
z*
1'
0"
#68
1&
0$
#69
0)
0*
0'
1"
#70
0,
z+
0%
1#
1!
0(
1'
0&
1$
#72
1&
0$
z)
1(
z*
0"
#74
0&
1$
#75
0)
0(
0*
1"
#76
z,
0#
0!
1(
0+
1%
0'
1&
0$
#78
0&
1$
z)
z*
1'
0"
#80
1&
0$
#81
0)
0*
0'
1"
#82
0,
z+
0%
1#
1!
0(
1'
0&
1$
#84
1&
0$
z)
1(
z*
0"
#86
0&
1$
#87
0)
0(
0*
1"
#88
z,
0#
0!
1(
0+
1%
0'
1&
0$
#90
0&
1$
z)
z*
1'
0"
#92
1&
0$
#93
0)
0*
0'
1"
#94
0,
z+
0%
1#
1!
0(
1'
0&
1$
#96
1&
0$
z)
1(
z*
0"
#98
0&
1$
#99
0)
0(
0*
1"
#100
z,
0#
0!
1(
0+
1%
0'
1&
0$
