nand/nand.v
module Nand(input_1, input_2, out);
	input input_1;
	input input_2;
	output out;

	wire input_1;
	wire input_2;
	wire out;

	wire intermediary;

	nmos n1(intermediary, 0, input_2);
	nmos n2(out, intermediary, input_1);

	pmos p1(out, 1, input_1);
	pmos p2(out, 1, input_2);
endmodule

sr_latch/sr_latch.v
module SR_latch(S, R, Q, Q_dot);
	input S;
	input R;
	output Q;
	output Q_dot;
	
	wire S;
	wire R;
	wire Q;
	wire Q_dot;
	
	Nand n1(S, Q_dot, Q);
	Nand n2(R, Q, Q_dot);
endmodule

sr_latch/sr_latch_tb.v
module test;
	initial begin
		# 100 $finish;
	end
	
	reg set = 1;
	reg reset = 0;

	reg out = 0;
	
	wire w_out;
	wire w_dot_out;
	
	SR_latch s1(set, reset, w_out, w_dot_out);
	
	always
	begin
		#5 reset = 1; 
		#0 set = 0;
		#5 set = 1;
		#5 reset = 0;
		#5 reset = 1;
	end
	
	always @(posedge set, posedge reset)
	begin
		assign out = w_out;
	end

	initial begin
		$dumpfile("sr_latch.vcd");
		$dumpvars(0, test);
		$monitor("At time %t, set = (%0d), reset = (%0d), output = (%0d)", $time, set, reset, out);
	end
endmodule

sr_latch/sr_latch.vcd
$date
	Tue Jun 25 21:07:54 2019
$end
$version
	Icarus Verilog
$end
$timescale
	1s
$end
$scope module test $end
$var wire 1 ! w_dot_out $end
$var wire 1 " w_out $end
$var reg 1 # out $end
$var reg 1 $ reset $end
$var reg 1 % set $end
$scope module s1 $end
$var wire 1 " Q $end
$var wire 1 ! Q_dot $end
$var wire 1 $ R $end
$var wire 1 % S $end
$scope module n1 $end
$var wire 1 % input_1 $end
$var wire 1 ! input_2 $end
$var wire 1 & intermediary $end
$var wire 1 " out $end
$upscope $end
$scope module n2 $end
$var wire 1 $ input_1 $end
$var wire 1 " input_2 $end
$var wire 1 ' intermediary $end
$var wire 1 ! out $end
$upscope $end
$upscope $end
$upscope $end
$enddefinitions $end
#0
$dumpvars
z'
0&
1%
0$
0#
0"
1!
$end
#5
0'
z&
0!
1#
1"
0%
1$
#10
1%
#15
0&
z'
0#
0"
1!
0$
#20
1$
#25
0'
z&
0!
1#
1"
0%
#30
1%
#35
0&
z'
0#
0"
1!
0$
#40
1$
#45
0'
z&
0!
1#
1"
0%
#50
1%
#55
0&
z'
0#
0"
1!
0$
#60
1$
#65
0'
z&
0!
1#
1"
0%
#70
1%
#75
0&
z'
0#
0"
1!
0$
#80
1$
#85
0'
z&
0!
1#
1"
0%
#90
1%
#95
0&
z'
0#
0"
1!
0$
#100
1$
